comptime/__about__.py
comptime/__init__.py
comptime/compiler.py
comptime/core.py
comptime/py.typed
comptime/types.py
comptime-0.1.0.dist-info/METADATA
comptime-0.1.0.dist-info/WHEEL
comptime-0.1.0.dist-info/licenses/LICENSE.txt
comptime-0.1.0.dist-info/RECORD
