Metadata-Version: 2.1
Name: comptime
Version: 0.1.0
Summary: "Comptime" accelerates Python code by precomputing complex calculations, turning them into simple lookups for faster execution.
Project-URL: Documentation, https://github.com/robinvandernoord/comptime#readme
Project-URL: Issues, https://github.com/robinvandernoord/comptime/issues
Project-URL: Source, https://github.com/robinvandernoord/comptime
Author-email: Robin van der Noord <robinvandernoord@gmail.com>
License-Expression: MIT
License-File: LICENSE.txt
Classifier: Development Status :: 4 - Beta
Classifier: Programming Language :: Python
Classifier: Programming Language :: Python :: 3.10
Classifier: Programming Language :: Python :: 3.11
Classifier: Programming Language :: Python :: 3.12
Classifier: Programming Language :: Python :: Implementation :: CPython
Classifier: Programming Language :: Python :: Implementation :: PyPy
Requires-Python: >=3.10
Requires-Dist: ast-comments
Provides-Extra: dev
Requires-Dist: hatch; extra == 'dev'
Requires-Dist: python-semantic-release<8; extra == 'dev'
Requires-Dist: su6[all]; extra == 'dev'
